LICENSE
MANIFEST.in
README.rst
setup.py
django_model_filters.egg-info/PKG-INFO
django_model_filters.egg-info/SOURCES.txt
django_model_filters.egg-info/dependency_links.txt
django_model_filters.egg-info/not-zip-safe
django_model_filters.egg-info/requires.txt
django_model_filters.egg-info/top_level.txt
model_filters/__init__.py
model_filters/models.py
model_filters/tests.py
model_filters/views.py
model_filters/static/model_filters/simple.css
model_filters/templates/model_filters/object_detail.html
model_filters/templates/model_filters/object_list.html
model_filters/templatetags/__init__.py
model_filters/templatetags/model_blocks.py
model_filters/templatetags/model_filters.py
model_filters/templatetags/model_nodes.py
model_filters/templatetags/model_tags.py