Metadata-Version: 1.0
Name: django-model-filters
Version: 0.8.0
Summary: Simple filters for generic object template blocks
Home-page: https://github.com/mjumbewu/django-model-filters/
Author: Mjumbe Wawatu Ukweli
Author-email: mjumbewu@kwawatu.com
License: UNKNOWN
Download-URL: https://github.com/mjumbewu/django-model-filters/downloads
Platform: UNKNOWN
Classifier: Development Status :: 4 - Beta
Classifier: Environment :: Web Environment
Classifier: Framework :: Django
Classifier: Intended Audience :: Developers
Classifier: License :: OSI Approved :: BSD License
Classifier: Operating System :: OS Independent
Classifier: Programming Language :: Python
Classifier: Topic :: Utilities
